{
    "forces": [
        {
            "radius": 0.001, 
            "pos": [
                0.28800000000000003, 
                0.4286666666666667
            ], 
            "dir": [
                0.9988681377244376, 
                0.04756514941544941
            ]
        }, 
        {
            "radius": 0.001, 
            "pos": [
                0.31738271604938273, 
                0.42960493827160495
            ], 
            "dir": [
                0.9998124454170366, 
                0.01936682702986996
            ]
        }, 
        {
            "radius": 0.001, 
            "pos": [
                0.34883950617283954, 
                0.4299506172839506
            ], 
            "dir": [
                0.9999893819780309, 
                0.004608245999898756
            ]
        }, 
        {
            "radius": 0.001, 
            "pos": [
                0.38133333333333336, 
                0.43000000000000005
            ], 
            "dir": [
                1.0, 
                0.0
            ]
        }, 
        {
            "radius": 0.001, 
            "pos": [
                0.4139753086419753, 
                0.4299506172839506
            ], 
            "dir": [
                0.9999895272605405, 
                -0.004576611108743892
            ]
        }, 
        {
            "radius": 0.001, 
            "pos": [
                0.4455802469135803, 
                0.42960493827160495
            ], 
            "dir": [
                0.9998124454170366, 
                -0.01936682702986996
            ]
        }, 
        {
            "radius": 0.001, 
            "pos": [
                0.4746666666666667, 
                0.4286666666666667
            ], 
            "dir": [
                0.9990561583550596, 
                -0.04343722427630694
            ]
        }, 
        {
            "radius": 0.001, 
            "pos": [
                0.4746666666666667, 
                0.44733333333333336
            ], 
            "dir": [
                -0.99970269064305, 
                -0.024382992454708534
            ]
        }, 
        {
            "radius": 0.001, 
            "pos": [
                0.4455802469135803, 
                0.4466913580246914
            ], 
            "dir": [
                -0.9998124454170366, 
                -0.01936682702986996
            ]
        }, 
        {
            "radius": 0.001, 
            "pos": [
                0.4139753086419753, 
                0.44619753086419756
            ], 
            "dir": [
                -0.9999345507760924, 
                -0.01144089875029854
            ]
        }, 
        {
            "radius": 0.001, 
            "pos": [
                0.38133333333333336, 
                0.446
            ], 
            "dir": [
                -1.0, 
                0.0
            ]
        }, 
        {
            "radius": 0.001, 
            "pos": [
                0.34883950617283954, 
                0.44619753086419756
            ], 
            "dir": [
                -0.9999336429111984, 
                0.01151997284459906
            ]
        }, 
        {
            "radius": 0.001, 
            "pos": [
                0.31738271604938273, 
                0.4466913580246914
            ], 
            "dir": [
                -0.9998124454170366, 
                0.019366827029869964
            ]
        }, 
        {
            "radius": 0.001, 
            "pos": [
                0.28800000000000003, 
                0.44733333333333336
            ], 
            "dir": [
                -0.9990561583550596, 
                0.04343722427630694
            ]
        }
    ]
}