{
    "font": "Magmatic Thin",
    "forces": [
        {
            "radius": 0.001,
            "pos": [
                0.5266666666666666,
                0.6553333333333333
            ],
            "dir": [
                0.0,
                1.0
            ]
        },
        {
            "radius": 0.001,
            "pos": [
                0.526,
                0.6709333333333334
            ],
            "dir": [
                -0.09150635872549731,
                0.9958044920127648
            ]
        },
        {
            "radius": 0.001,
            "pos": [
                0.5238933333333333,
                0.6849333333333334
            ],
            "dir": [
                -0.2131670752167256,
                0.9770157614099922
            ]
        },
        {
            "radius": 0.001,
            "pos": [
                0.5201866666666667,
                0.6973333333333334
            ],
            "dir": [
                -0.36585094559670306,
                0.9306734580968764
            ]
        },
        {
            "radius": 0.001,
            "pos": [
                0.5147200000000001,
                0.7081333333333334
            ],
            "dir": [
                -0.5390536964233673,
                0.8422714006615113
            ]
        },
        {
            "radius": 0.001,
            "pos": [
                0.5073333333333334,
                0.7173333333333334
            ],
            "dir": [
                -0.7071067811865475,
                0.7071067811865475
            ]
        },
        {
            "radius": 0.001,
            "pos": [
                0.49818666666666667,
                0.724464
            ],
            "dir": [
                -0.8527544148434507,
                0.5223120790916136
            ]
        },
        {
            "radius": 0.001,
            "pos": [
                0.48696,
                0.7298986666666667
            ],
            "dir": [
                -0.93511003214167,
                0.3543574858642118
            ]
        },
        {
            "radius": 0.001,
            "pos": [
                0.47397333333333336,
                0.7337013333333333
            ],
            "dir": [
                -0.9769296510654483,
                0.21356136558174912
            ]
        },
        {
            "radius": 0.001,
            "pos": [
                0.45954666666666666,
                0.735936
            ],
            "dir": [
                -0.9952446390327747,
                0.09740692211810134
            ]
        },
        {
            "radius": 0.001,
            "pos": [
                0.444,
                0.7366666666666667
            ],
            "dir": [
                -1.0,
                0.0
            ]
        },
        {
            "radius": 0.001,
            "pos": [
                0.4303117283950617,
                0.7362561728395062
            ],
            "dir": [
                -0.998011945793103,
                -0.06302504307229173
            ]
        },
        {
            "radius": 0.001,
            "pos": [
                0.4173827160493827,
                0.7349382716049383
            ],
            "dir": [
                -0.9895940429038554,
                -0.14388756113438847
            ]
        },
        {
            "radius": 0.001,
            "pos": [
                0.40541666666666665,
                0.7325833333333334
            ],
            "dir": [
                -0.9688816333721296,
                -0.2475245048760915
            ]
        },
        {
            "radius": 0.001,
            "pos": [
                0.3946172839506173,
                0.7290617283950618
            ],
            "dir": [
                -0.9256545461107231,
                -0.3783697414759159
            ]
        },
        {
            "radius": 0.001,
            "pos": [
                0.3851882716049383,
                0.7242438271604938
            ],
            "dir": [
                -0.844180458182474,
                -0.5360590956441538
            ]
        },
        {
            "radius": 0.001,
            "pos": [
                0.37733333333333335,
                0.718
            ],
            "dir": [
                -0.7071067811865476,
                -0.7071067811865476
            ]
        },
        {
            "radius": 0.001,
            "pos": [
                0.36987733333333334,
                0.7087946666666667
            ],
            "dir": [
                -0.5460228179484676,
                -0.8377703040091685
            ]
        },
        {
            "radius": 0.001,
            "pos": [
                0.36424533333333337,
                0.6979573333333333
            ],
            "dir": [
                -0.3772968873135194,
                -0.9260923597695477
            ]
        },
        {
            "radius": 0.001,
            "pos": [
                0.36034133333333335,
                0.6854560000000001
            ],
            "dir": [
                -0.2243474467190317,
                -0.9745092216857937
            ]
        },
        {
            "radius": 0.001,
            "pos": [
                0.35806933333333335,
                0.6712586666666667
            ],
            "dir": [
                -0.0983518685274201,
                -0.9951517019817456
            ]
        },
        {
            "radius": 0.001,
            "pos": [
                0.35733333333333334,
                0.6553333333333333
            ],
            "dir": [
                0.0,
                -1.0
            ]
        },
        {
            "radius": 0.001,
            "pos": [
                0.3578612572001002,
                0.6426621587778614
            ],
            "dir": [
                0.08559827099061124,
                -0.9963297325702057
            ]
        },
        {
            "radius": 0.001,
            "pos": [
                0.35944102178812926,
                0.6307242674680691
            ],
            "dir": [
                0.17807944151092356,
                -0.984016113948932
            ]
        },
        {
            "radius": 0.001,
            "pos": [
                0.3620666165790133,
                0.6193603806661658
            ],
            "dir": [
                0.2720433113152456,
                -0.9622850080764204
            ]
        },
        {
            "radius": 0.001,
            "pos": [
                0.36573203105434515,
                0.6084112196343601
            ],
            "dir": [
                0.3613436372772621,
                -0.932432719180981
            ]
        },
        {
            "radius": 0.001,
            "pos": [
                0.3704312546957175,
                0.597717505634861
            ],
            "dir": [
                0.44074948730500074,
                -0.8976301518110779
            ]
        },
        {
            "radius": 0.001,
            "pos": [
                0.37615827698472326,
                0.5871199599298773
            ],
            "dir": [
                0.5071482324679394,
                -0.8618588459281745
            ]
        },
        {
            "radius": 0.001,
            "pos": [
                0.3829070874029552,
                0.5764593037816179
            ],
            "dir": [
                0.5597176340143007,
                -0.8286833956182742
            ]
        },
        {
            "radius": 0.001,
            "pos": [
                0.39067167543200604,
                0.5655762584522915
            ],
            "dir": [
                0.5993029085188318,
                -0.8005223443732652
            ]
        },
        {
            "radius": 0.001,
            "pos": [
                0.3994460305534686,
                0.5543115452041072
            ],
            "dir": [
                0.6275915014930485,
                -0.7785428101612016
            ]
        },
        {
            "radius": 0.001,
            "pos": [
                0.40922414224893566,
                0.5425058852992737
            ],
            "dir": [
                0.6464844005275797,
                -0.7629272048331321
            ]
        },
        {
            "radius": 0.001,
            "pos": [
                0.42000000000000004,
                0.53
            ],
            "dir": [
                0.6560349686387517,
                -0.7547304948941391
            ]
        },
        {
            "radius": 0.001,
            "pos": [
                0.4286923076923077,
                0.52
            ],
            "dir": [
                0.6560349686387517,
                -0.7547304948941391
            ]
        },
        {
            "radius": 0.001,
            "pos": [
                0.43738461538461537,
                0.51
            ],
            "dir": [
                0.6560349686387517,
                -0.7547304948941391
            ]
        },
        {
            "radius": 0.001,
            "pos": [
                0.44607692307692315,
                0.5
            ],
            "dir": [
                0.6560349686387517,
                -0.7547304948941391
            ]
        },
        {
            "radius": 0.001,
            "pos": [
                0.45476923076923076,
                0.49
            ],
            "dir": [
                0.6560349686387517,
                -0.7547304948941391
            ]
        },
        {
            "radius": 0.001,
            "pos": [
                0.4634615384615385,
                0.48
            ],
            "dir": [
                0.6560349686387517,
                -0.7547304948941391
            ]
        },
        {
            "radius": 0.001,
            "pos": [
                0.47215384615384615,
                0.47000000000000003
            ],
            "dir": [
                0.6560349686387517,
                -0.7547304948941391
            ]
        },
        {
            "radius": 0.001,
            "pos": [
                0.48084615384615387,
                0.46
            ],
            "dir": [
                0.6560349686387517,
                -0.7547304948941391
            ]
        },
        {
            "radius": 0.001,
            "pos": [
                0.4895384615384616,
                0.45
            ],
            "dir": [
                0.6560349686387517,
                -0.7547304948941391
            ]
        },
        {
            "radius": 0.001,
            "pos": [
                0.49823076923076925,
                0.44000000000000006
            ],
            "dir": [
                0.6560349686387517,
                -0.7547304948941391
            ]
        },
        {
            "radius": 0.001,
            "pos": [
                0.5069230769230769,
                0.43000000000000005
            ],
            "dir": [
                0.6560349686387517,
                -0.7547304948941391
            ]
        },
        {
            "radius": 0.001,
            "pos": [
                0.5156153846153846,
                0.42000000000000004
            ],
            "dir": [
                0.6560349686387517,
                -0.7547304948941391
            ]
        },
        {
            "radius": 0.001,
            "pos": [
                0.5243076923076924,
                0.41000000000000003
            ],
            "dir": [
                0.6560349686387517,
                -0.7547304948941391
            ]
        },
        {
            "radius": 0.001,
            "pos": [
                0.533,
                0.4
            ],
            "dir": [
                0.6560349686387517,
                -0.7547304948941391
            ]
        },
        {
            "radius": 0.001,
            "pos": [
                0.5416923076923077,
                0.39
            ],
            "dir": [
                0.6560349686387517,
                -0.7547304948941391
            ]
        },
        {
            "radius": 0.001,
            "pos": [
                0.5503846153846155,
                0.38
            ],
            "dir": [
                0.6560349686387517,
                -0.7547304948941391
            ]
        },
        {
            "radius": 0.001,
            "pos": [
                0.5590769230769231,
                0.37
            ],
            "dir": [
                0.6560349686387517,
                -0.7547304948941391
            ]
        },
        {
            "radius": 0.001,
            "pos": [
                0.5677692307692308,
                0.36
            ],
            "dir": [
                0.6560349686387517,
                -0.7547304948941391
            ]
        },
        {
            "radius": 0.001,
            "pos": [
                0.5764615384615385,
                0.35000000000000003
            ],
            "dir": [
                0.6560349686387517,
                -0.7547304948941391
            ]
        },
        {
            "radius": 0.001,
            "pos": [
                0.5851538461538461,
                0.34
            ],
            "dir": [
                0.6560349686387517,
                -0.7547304948941391
            ]
        },
        {
            "radius": 0.001,
            "pos": [
                0.5938461538461539,
                0.33
            ],
            "dir": [
                0.6560349686387517,
                -0.7547304948941391
            ]
        },
        {
            "radius": 0.001,
            "pos": [
                0.6025384615384616,
                0.32
            ],
            "dir": [
                0.6560349686387517,
                -0.7547304948941391
            ]
        },
        {
            "radius": 0.001,
            "pos": [
                0.6112307692307692,
                0.31
            ],
            "dir": [
                0.6560349686387517,
                -0.7547304948941391
            ]
        },
        {
            "radius": 0.001,
            "pos": [
                0.6199230769230769,
                0.30000000000000004
            ],
            "dir": [
                0.6560349686387517,
                -0.7547304948941391
            ]
        },
        {
            "radius": 0.001,
            "pos": [
                0.6286153846153846,
                0.29000000000000004
            ],
            "dir": [
                0.6560349686387517,
                -0.7547304948941391
            ]
        },
        {
            "radius": 0.001,
            "pos": [
                0.6373076923076924,
                0.28
            ],
            "dir": [
                0.6560349686387517,
                -0.7547304948941391
            ]
        },
        {
            "radius": 0.001,
            "pos": [
                0.646,
                0.27
            ],
            "dir": [
                1.0,
                0.0
            ]
        },
        {
            "radius": 0.001,
            "pos": [
                0.659,
                0.27
            ],
            "dir": [
                1.0,
                0.0
            ]
        },
        {
            "radius": 0.001,
            "pos": [
                0.672,
                0.27
            ],
            "dir": [
                -0.6564075750224381,
                0.7544064524201541
            ]
        },
        {
            "radius": 0.001,
            "pos": [
                0.663547619047619,
                0.27971428571428575
            ],
            "dir": [
                -0.6564075750224381,
                0.7544064524201541
            ]
        },
        {
            "radius": 0.001,
            "pos": [
                0.6550952380952381,
                0.2894285714285714
            ],
            "dir": [
                -0.6564075750224381,
                0.7544064524201541
            ]
        },
        {
            "radius": 0.001,
            "pos": [
                0.6466428571428571,
                0.29914285714285715
            ],
            "dir": [
                -0.6564075750224381,
                0.7544064524201541
            ]
        },
        {
            "radius": 0.001,
            "pos": [
                0.6381904761904762,
                0.3088571428571429
            ],
            "dir": [
                -0.6564075750224381,
                0.7544064524201541
            ]
        },
        {
            "radius": 0.001,
            "pos": [
                0.6297380952380953,
                0.3185714285714286
            ],
            "dir": [
                -0.6564075750224381,
                0.7544064524201541
            ]
        },
        {
            "radius": 0.001,
            "pos": [
                0.6212857142857143,
                0.3282857142857143
            ],
            "dir": [
                -0.6564075750224381,
                0.7544064524201541
            ]
        },
        {
            "radius": 0.001,
            "pos": [
                0.6128333333333333,
                0.338
            ],
            "dir": [
                -0.6564075750224381,
                0.7544064524201541
            ]
        },
        {
            "radius": 0.001,
            "pos": [
                0.6043809523809525,
                0.34771428571428575
            ],
            "dir": [
                -0.6564075750224381,
                0.7544064524201541
            ]
        },
        {
            "radius": 0.001,
            "pos": [
                0.5959285714285714,
                0.35742857142857143
            ],
            "dir": [
                -0.6564075750224381,
                0.7544064524201541
            ]
        },
        {
            "radius": 0.001,
            "pos": [
                0.5874761904761905,
                0.36714285714285716
            ],
            "dir": [
                -0.6564075750224381,
                0.7544064524201541
            ]
        },
        {
            "radius": 0.001,
            "pos": [
                0.5790238095238096,
                0.3768571428571429
            ],
            "dir": [
                -0.6564075750224381,
                0.7544064524201541
            ]
        },
        {
            "radius": 0.001,
            "pos": [
                0.5705714285714286,
                0.38657142857142857
            ],
            "dir": [
                -0.6564075750224381,
                0.7544064524201541
            ]
        },
        {
            "radius": 0.001,
            "pos": [
                0.5621190476190476,
                0.39628571428571435
            ],
            "dir": [
                -0.6564075750224381,
                0.7544064524201541
            ]
        },
        {
            "radius": 0.001,
            "pos": [
                0.5536666666666668,
                0.406
            ],
            "dir": [
                -0.6564075750224381,
                0.7544064524201541
            ]
        },
        {
            "radius": 0.001,
            "pos": [
                0.5452142857142857,
                0.4157142857142857
            ],
            "dir": [
                -0.6564075750224381,
                0.7544064524201541
            ]
        },
        {
            "radius": 0.001,
            "pos": [
                0.5367619047619048,
                0.42542857142857143
            ],
            "dir": [
                -0.6564075750224381,
                0.7544064524201541
            ]
        },
        {
            "radius": 0.001,
            "pos": [
                0.5283095238095239,
                0.43514285714285716
            ],
            "dir": [
                -0.6564075750224381,
                0.7544064524201541
            ]
        },
        {
            "radius": 0.001,
            "pos": [
                0.5198571428571429,
                0.44485714285714284
            ],
            "dir": [
                -0.6564075750224381,
                0.7544064524201541
            ]
        },
        {
            "radius": 0.001,
            "pos": [
                0.5114047619047619,
                0.4545714285714286
            ],
            "dir": [
                -0.6564075750224381,
                0.7544064524201541
            ]
        },
        {
            "radius": 0.001,
            "pos": [
                0.502952380952381,
                0.4642857142857143
            ],
            "dir": [
                -0.6564075750224381,
                0.7544064524201541
            ]
        },
        {
            "radius": 0.001,
            "pos": [
                0.49450000000000005,
                0.474
            ],
            "dir": [
                -0.6564075750224381,
                0.7544064524201541
            ]
        },
        {
            "radius": 0.001,
            "pos": [
                0.48604761904761906,
                0.4837142857142857
            ],
            "dir": [
                -0.6564075750224381,
                0.7544064524201541
            ]
        },
        {
            "radius": 0.001,
            "pos": [
                0.47759523809523813,
                0.49342857142857144
            ],
            "dir": [
                -0.6564075750224381,
                0.7544064524201541
            ]
        },
        {
            "radius": 0.001,
            "pos": [
                0.4691428571428572,
                0.5031428571428571
            ],
            "dir": [
                -0.6564075750224381,
                0.7544064524201541
            ]
        },
        {
            "radius": 0.001,
            "pos": [
                0.4606904761904762,
                0.5128571428571429
            ],
            "dir": [
                -0.6564075750224381,
                0.7544064524201541
            ]
        },
        {
            "radius": 0.001,
            "pos": [
                0.4522380952380952,
                0.5225714285714287
            ],
            "dir": [
                -0.6564075750224381,
                0.7544064524201541
            ]
        },
        {
            "radius": 0.001,
            "pos": [
                0.44378571428571434,
                0.5322857142857143
            ],
            "dir": [
                -0.6564075750224381,
                0.7544064524201541
            ]
        },
        {
            "radius": 0.001,
            "pos": [
                0.43533333333333335,
                0.542
            ],
            "dir": [
                -0.6527090256285246,
                0.7576086904616803
            ]
        },
        {
            "radius": 0.001,
            "pos": [
                0.42465600000000003,
                0.5545340000000001
            ],
            "dir": [
                -0.64268418917965,
                0.7661312113329516
            ]
        },
        {
            "radius": 0.001,
            "pos": [
                0.41503466666666666,
                0.5662720000000001
            ],
            "dir": [
                -0.6230883811907169,
                0.7821514362482063
            ]
        },
        {
            "radius": 0.001,
            "pos": [
                0.40648533333333337,
                0.577418
            ],
            "dir": [
                -0.5914341014997474,
                0.8063533366850951
            ]
        },
        {
            "radius": 0.001,
            "pos": [
                0.39902400000000005,
                0.588176
            ],
            "dir": [
                -0.5450548709059507,
                0.8384003743449173
            ]
        },
        {
            "radius": 0.001,
            "pos": [
                0.39266666666666666,
                0.59875
            ],
            "dir": [
                -0.48175931386661497,
                0.8763035795332392
            ]
        },
        {
            "radius": 0.001,
            "pos": [
                0.38742933333333335,
                0.6093440000000001
            ],
            "dir": [
                -0.40103496567152463,
                0.9160627469277632
            ]
        },
        {
            "radius": 0.001,
            "pos": [
                0.383328,
                0.620162
            ],
            "dir": [
                -0.3054542157352126,
                0.9522067643582387
            ]
        },
        {
            "radius": 0.001,
            "pos": [
                0.3803786666666667,
                0.6314080000000001
            ],
            "dir": [
                -0.20121175523388474,
                0.9795477678784733
            ]
        },
        {
            "radius": 0.001,
            "pos": [
                0.37859733333333334,
                0.643286
            ],
            "dir": [
                -0.09675480598648062,
                0.9953082474884444
            ]
        },
        {
            "radius": 0.001,
            "pos": [
                0.378,
                0.656
            ],
            "dir": [
                0.0,
                1.0
            ]
        },
        {
            "radius": 0.001,
            "pos": [
                0.3786666666666667,
                0.6709791666666667
            ],
            "dir": [
                0.09817809390894433,
                0.9951688609861176
            ]
        },
        {
            "radius": 0.001,
            "pos": [
                0.38083333333333336,
                0.6838333333333333
            ],
            "dir": [
                0.2473832452658204,
                0.9689177106244632
            ]
        },
        {
            "radius": 0.001,
            "pos": [
                0.38475000000000004,
                0.6944375
            ],
            "dir": [
                0.45894264763351417,
                0.8884658947777005
            ]
        },
        {
            "radius": 0.001,
            "pos": [
                0.3906666666666667,
                0.7026666666666667
            ],
            "dir": [
                0.7071067811865475,
                0.7071067811865475
            ]
        },
        {
            "radius": 0.001,
            "pos": [
                0.39857600000000004,
                0.7088693333333334
            ],
            "dir": [
                0.8538305851539356,
                0.5205509887183846
            ]
        },
        {
            "radius": 0.001,
            "pos": [
                0.40786133333333335,
                0.713248
            ],
            "dir": [
                0.94181040629235,
                0.3361445501557905
            ]
        },
        {
            "radius": 0.001,
            "pos": [
                0.41845866666666665,
                0.7160586666666666
            ],
            "dir": [
                0.9827769639779433,
                0.1847956684402971
            ]
        },
        {
            "radius": 0.001,
            "pos": [
                0.430304,
                0.7175573333333334
            ],
            "dir": [
                0.9972326688822241,
                0.07434382364417602
            ]
        },
        {
            "radius": 0.001,
            "pos": [
                0.44333333333333336,
                0.718
            ],
            "dir": [
                1.0,
                0.0
            ]
        },
        {
            "radius": 0.001,
            "pos": [
                0.45865625,
                0.7171979166666667
            ],
            "dir": [
                0.9936215193470729,
                -0.11276646793446438
            ]
        },
        {
            "radius": 0.001,
            "pos": [
                0.4724166666666667,
                0.7145833333333333
            ],
            "dir": [
                0.9625747858429554,
                -0.2710162018392787
            ]
        },
        {
            "radius": 0.001,
            "pos": [
                0.48430208333333336,
                0.70984375
            ],
            "dir": [
                0.8781855664920153,
                -0.4783200924120775
            ]
        },
        {
            "radius": 0.001,
            "pos": [
                0.494,
                0.7026666666666667
            ],
            "dir": [
                0.7071067811865475,
                -0.7071067811865475
            ]
        },
        {
            "radius": 0.001,
            "pos": [
                0.50009375,
                0.6941458333333334
            ],
            "dir": [
                0.447213595499958,
                -0.894427190999916
            ]
        },
        {
            "radius": 0.001,
            "pos": [
                0.50375,
                0.6835
            ],
            "dir": [
                0.2180296293229264,
                -0.975942150302623
            ]
        },
        {
            "radius": 0.001,
            "pos": [
                0.50553125,
                0.6706041666666667
            ],
            "dir": [
                0.073136939914236,
                -0.9973219079214001
            ]
        },
        {
            "radius": 0.001,
            "pos": [
                0.506,
                0.6553333333333333
            ],
            "dir": [
                0.0,
                -1.0
            ]
        },
        {
            "radius": 0.001,
            "pos": [
                0.50511394941147,
                0.6424618081642874
            ],
            "dir": [
                -0.13876710602548065,
                -0.9903250427437008
            ]
        },
        {
            "radius": 0.001,
            "pos": [
                0.5025479589281242,
                0.6303446030553469
            ],
            "dir": [
                -0.2746237980436341,
                -0.9615517508424022
            ]
        },
        {
            "radius": 0.001,
            "pos": [
                0.4984402704733283,
                0.6189095917856249
            ],
            "dir": [
                -0.3986263964932815,
                -0.9171134041212032
            ]
        },
        {
            "radius": 0.001,
            "pos": [
                0.4929291259704483,
                0.6080846481342349
            ],
            "dir": [
                -0.5048573737850831,
                -0.8632027757918929
            ]
        },
        {
            "radius": 0.001,
            "pos": [
                0.48615276734285,
                0.5977976458802905
            ],
            "dir": [
                -0.5912956524102504,
                -0.8064548663383069
            ]
        },
        {
            "radius": 0.001,
            "pos": [
                0.47824943651389934,
                0.587976458802905
            ],
            "dir": [
                -0.6589456981693961,
                -0.7521905123464715
            ]
        },
        {
            "radius": 0.001,
            "pos": [
                0.4693573754069622,
                0.578548960681192
            ],
            "dir": [
                -0.7103562225298652,
                -0.7038423382499099
            ]
        },
        {
            "radius": 0.001,
            "pos": [
                0.4596148259454045,
                0.569443025294265
            ],
            "dir": [
                -0.7484321693335396,
                -0.6632113448265883
            ]
        },
        {
            "radius": 0.001,
            "pos": [
                0.4491600300525921,
                0.5605865264212372
            ],
            "dir": [
                -0.7757826559921576,
                -0.6310002144704498
            ]
        },
        {
            "radius": 0.001,
            "pos": [
                0.43813122965189083,
                0.5519073378412221
            ],
            "dir": [
                -0.7944750813105738,
                -0.6072967521538026
            ]
        },
        {
            "radius": 0.001,
            "pos": [
                0.4266666666666667,
                0.5433333333333333
            ],
            "dir": [
                -0.939793423488437,
                -0.3417430630867044
            ]
        },
        {
            "radius": 0.001,
            "pos": [
                0.41933333333333334,
                0.5406666666666666
            ],
            "dir": [
                -0.8279186904883319,
                -0.5608481451695152
            ]
        },
        {
            "radius": 0.001,
            "pos": [
                0.4077384440104167,
                0.5326936848958334
            ],
            "dir": [
                -0.8195654588790502,
                -0.572985565797579
            ]
        },
        {
            "radius": 0.001,
            "pos": [
                0.39626171875000005,
                0.5245078125
            ],
            "dir": [
                -0.8081243486567079,
                -0.5890119159305451
            ]
        },
        {
            "radius": 0.001,
            "pos": [
                0.3849900716145833,
                0.5160836588541666
            ],
            "dir": [
                -0.7932284820726512,
                -0.6089241128652384
            ]
        },
        {
            "radius": 0.001,
            "pos": [
                0.3740104166666667,
                0.5073958333333334
            ],
            "dir": [
                -0.7743812299462532,
                -0.6327192985099539
            ]
        },
        {
            "radius": 0.001,
            "pos": [
                0.36340966796875,
                0.49841894531250003
            ],
            "dir": [
                -0.7509488745656583,
                -0.6603603469232319
            ]
        },
        {
            "radius": 0.001,
            "pos": [
                0.35327473958333333,
                0.4891276041666667
            ],
            "dir": [
                -0.7221576762651811,
                -0.6917284804106839
            ]
        },
        {
            "radius": 0.001,
            "pos": [
                0.3436925455729167,
                0.47949641927083336
            ],
            "dir": [
                -0.6871033839428572,
                -0.7265596601616928
            ]
        },
        {
            "radius": 0.001,
            "pos": [
                0.33475,
                0.46950000000000003
            ],
            "dir": [
                -0.644785333834661,
                -0.7643637048367254
            ]
        },
        {
            "radius": 0.001,
            "pos": [
                0.32653401692708334,
                0.45911295572916666
            ],
            "dir": [
                -0.5941814628194676,
                -0.8043310196938308
            ]
        },
        {
            "radius": 0.001,
            "pos": [
                0.3191315104166667,
                0.44830989583333336
            ],
            "dir": [
                -0.5343818545616903,
                -0.8452431801057069
            ]
        },
        {
            "radius": 0.001,
            "pos": [
                0.31262939453125005,
                0.4370654296875
            ],
            "dir": [
                -0.4647910669149763,
                -0.8854203883557449
            ]
        },
        {
            "radius": 0.001,
            "pos": [
                0.30711458333333336,
                0.4253541666666667
            ],
            "dir": [
                -0.38538608692046505,
                -0.9227554193870291
            ]
        },
        {
            "radius": 0.001,
            "pos": [
                0.3026739908854167,
                0.4131507161458333
            ],
            "dir": [
                -0.2969747979020397,
                -0.9548853174130612
            ]
        },
        {
            "radius": 0.001,
            "pos": [
                0.29939453125000004,
                0.4004296875
            ],
            "dir": [
                -0.20135367417774466,
                -0.9795186051806891
            ]
        },
        {
            "radius": 0.001,
            "pos": [
                0.29736311848958336,
                0.3871656901041667
            ],
            "dir": [
                -0.10125071874255166,
                -0.9948609410134247
            ]
        },
        {
            "radius": 0.001,
            "pos": [
                0.2966666666666667,
                0.37333333333333335
            ],
            "dir": [
                0.0,
                -1.0
            ]
        },
        {
            "radius": 0.001,
            "pos": [
                0.2975648611743287,
                0.35549931725079653
            ],
            "dir": [
                0.10487707222772824,
                -0.9944851933140784
            ]
        },
        {
            "radius": 0.001,
            "pos": [
                0.3002072523137612,
                0.33948960703990294
            ],
            "dir": [
                0.2247995242270624,
                -0.9744050358589526
            ]
        },
        {
            "radius": 0.001,
            "pos": [
                0.3045155515096344,
                0.32523501744803524
            ],
            "dir": [
                0.3566260292632178,
                -0.9342472238395738
            ]
        },
        {
            "radius": 0.001,
            "pos": [
                0.31041147018661813,
                0.31266636322257624
            ],
            "dir": [
                0.49334923882505605,
                -0.8698313218956522
            ]
        },
        {
            "radius": 0.001,
            "pos": [
                0.3178167197693825,
                0.30171445911090883
            ],
            "dir": [
                0.6247206271103448,
                -0.7808483451111731
            ]
        },
        {
            "radius": 0.001,
            "pos": [
                0.3266530116825975,
                0.2923101198604157
            ],
            "dir": [
                0.7401768796224624,
                -0.6724122149934181
            ]
        },
        {
            "radius": 0.001,
            "pos": [
                0.3368420573509331,
                0.2843841602184798
            ],
            "dir": [
                0.8326307769923125,
                -0.5538284835625359
            ]
        },
        {
            "radius": 0.001,
            "pos": [
                0.34830556819905933,
                0.2778673949324837
            ],
            "dir": [
                0.9003737743376002,
                -0.4351173019831135
            ]
        },
        {
            "radius": 0.001,
            "pos": [
                0.36096525565164617,
                0.27269063874981037
            ],
            "dir": [
                0.946094191166334,
                -0.3238916198998059
            ]
        },
        {
            "radius": 0.001,
            "pos": [
                0.3747428311333637,
                0.2687847064178425
            ],
            "dir": [
                0.9745226757718487,
                -0.22428899751542922
            ]
        },
        {
            "radius": 0.001,
            "pos": [
                0.3895600060688818,
                0.266080412683963
            ],
            "dir": [
                0.9904920502723752,
                -0.1375699761838557
            ]
        },
        {
            "radius": 0.001,
            "pos": [
                0.40533849188287063,
                0.2645085722955546
            ],
            "dir": [
                0.9979981976358285,
                -0.06324237120505204
            ]
        },
        {
            "radius": 0.001,
            "pos": [
                0.42200000000000004,
                0.264
            ],
            "dir": [
                1.0,
                0.0
            ]
        },
        {
            "radius": 0.001,
            "pos": [
                0.4367223703703704,
                0.2645212839506173
            ],
            "dir": [
                0.9973980472602327,
                0.07209115980114758
            ]
        },
        {
            "radius": 0.001,
            "pos": [
                0.4507656296296296,
                0.26607249382716053
            ],
            "dir": [
                0.9888983800241656,
                0.14859338473021225
            ]
        },
        {
            "radius": 0.001,
            "pos": [
                0.464144,
                0.2686346666666667
            ],
            "dir": [
                0.9735734776898487,
                0.22837399926194243
            ]
        },
        {
            "radius": 0.001,
            "pos": [
                0.4768717037037037,
                0.27218883950617284
            ],
            "dir": [
                0.9507737668456127,
                0.3098858568541081
            ]
        },
        {
            "radius": 0.001,
            "pos": [
                0.488962962962963,
                0.27671604938271605
            ],
            "dir": [
                0.9202788221077183,
                0.3912631973237846
            ]
        },
        {
            "radius": 0.001,
            "pos": [
                0.500432,
                0.28219733333333336
            ],
            "dir": [
                0.8823996187023222,
                0.47050070447768344
            ]
        },
        {
            "radius": 0.001,
            "pos": [
                0.511293037037037,
                0.2886137283950617
            ],
            "dir": [
                0.8379910847068912,
                0.5456839212875599
            ]
        },
        {
            "radius": 0.001,
            "pos": [
                0.5215602962962963,
                0.2959462716049383
            ],
            "dir": [
                0.7883601051195673,
                0.615214064091406
            ]
        },
        {
            "radius": 0.001,
            "pos": [
                0.531248,
                0.304176
            ],
            "dir": [
                0.7350911172088183,
                0.6779683247768228
            ]
        },
        {
            "radius": 0.001,
            "pos": [
                0.5403703703703704,
                0.313283950617284
            ],
            "dir": [
                0.6798393642508436,
                0.733361056243791
            ]
        },
        {
            "radius": 0.001,
            "pos": [
                0.5489416296296297,
                0.3232511604938272
            ],
            "dir": [
                0.6241460496313341,
                0.7813076914568295
            ]
        },
        {
            "radius": 0.001,
            "pos": [
                0.556976,
                0.33405866666666667
            ],
            "dir": [
                0.5693115674894653,
                0.8221218517486858
            ]
        },
        {
            "radius": 0.001,
            "pos": [
                0.5644877037037037,
                0.3456875061728395
            ],
            "dir": [
                0.5163365808942897,
                0.8563857397402146
            ]
        },
        {
            "radius": 0.001,
            "pos": [
                0.571490962962963,
                0.3581187160493827
            ],
            "dir": [
                0.46591996830477084,
                0.884826866191845
            ]
        },
        {
            "radius": 0.001,
            "pos": [
                0.5780000000000001,
                0.37133333333333335
            ],
            "dir": [
                0.41128886693508654,
                0.9115050564507323
            ]
        },
        {
            "radius": 0.001,
            "pos": [
                0.582229052174503,
                0.38118719044711313
            ],
            "dir": [
                0.3778799565142334,
                0.9258545989866881
            ]
        },
        {
            "radius": 0.001,
            "pos": [
                0.5862130402333945,
                0.3914513874754054
            ],
            "dir": [
                0.3462006979368479,
                0.9381604749444732
            ]
        },
        {
            "radius": 0.001,
            "pos": [
                0.5899560350091594,
                0.40212103941922794
            ],
            "dir": [
                0.3162490813098312,
                0.9486761926867818
            ]
        },
        {
            "radius": 0.001,
            "pos": [
                0.5934621073342832,
                0.4131912612795984
            ],
            "dir": [
                0.2879952677484357,
                0.9576318320495131
            ]
        },
        {
            "radius": 0.001,
            "pos": [
                0.5967353280412511,
                0.42465716805753445
            ],
            "dir": [
                0.2613893169917176,
                0.9652334561973095
            ]
        },
        {
            "radius": 0.001,
            "pos": [
                0.5997797679625483,
                0.4365138747540539
            ],
            "dir": [
                0.23636749322234102,
                0.9716637320327371
            ]
        },
        {
            "radius": 0.001,
            "pos": [
                0.6025994979306601,
                0.44875649637017434
            ],
            "dir": [
                0.21285726527258347,
                0.9770833048520874
            ]
        },
        {
            "radius": 0.001,
            "pos": [
                0.6051985887780718,
                0.4613801479069136
            ],
            "dir": [
                0.1907811705852565,
                0.9816325916299433
            ]
        },
        {
            "radius": 0.001,
            "pos": [
                0.6075811113372684,
                0.4743799443652894
            ],
            "dir": [
                0.17005972772334874,
                0.985433756782596
            ]
        },
        {
            "radius": 0.001,
            "pos": [
                0.6097511364407355,
                0.4877510007463193
            ],
            "dir": [
                0.15061357528454014,
                0.9885927123644034
            ]
        },
        {
            "radius": 0.001,
            "pos": [
                0.611712734920958,
                0.5014884320510211
            ],
            "dir": [
                0.1323649965615458,
                0.991201043020669
            ]
        },
        {
            "radius": 0.001,
            "pos": [
                0.6134699776104213,
                0.5155873532804125
            ],
            "dir": [
                0.11523896617236572,
                0.993337797869146
            ]
        },
        {
            "radius": 0.001,
            "pos": [
                0.6150269353416107,
                0.5300428794355112
            ],
            "dir": [
                0.09916383132368096,
                0.9950711203513086
            ]
        },
        {
            "radius": 0.001,
            "pos": [
                0.6163876789470113,
                0.5448501255173349
            ],
            "dir": [
                0.08407171859767872,
                0.9964597062260133
            ]
        },
        {
            "radius": 0.001,
            "pos": [
                0.6175562792591085,
                0.5600042065269014
            ],
            "dir": [
                0.06989873816967253,
                0.9975540919680936
            ]
        },
        {
            "radius": 0.001,
            "pos": [
                0.6185368071103874,
                0.5755002374652283
            ],
            "dir": [
                0.05658504144035073,
                0.998397782992928
            ]
        },
        {
            "radius": 0.001,
            "pos": [
                0.6193333333333333,
                0.5913333333333334
            ],
            "dir": [
                -0.997630328422983,
                0.06880209161537815
            ]
        },
        {
            "radius": 0.001,
            "pos": [
                0.6096666666666667,
                0.5920000000000001
            ],
            "dir": [
                -0.997630328422983,
                0.06880209161537815
            ]
        },
        {
            "radius": 0.001,
            "pos": [
                0.6000000000000001,
                0.5926666666666667
            ],
            "dir": [
                -0.031234752377721213,
                -0.9995120760870788
            ]
        },
        {
            "radius": 0.001,
            "pos": [
                0.5994386322002849,
                0.5777340389442975
            ],
            "dir": [
                -0.04406187312221057,
                -0.999028804057702
            ]
        },
        {
            "radius": 0.001,
            "pos": [
                0.5986924486057399,
                0.5630603161679897
            ],
            "dir": [
                -0.05768653176628111,
                -0.9983347454900975
            ]
        },
        {
            "radius": 0.001,
            "pos": [
                0.5977565642173825,
                0.548655268335708
            ],
            "dir": [
                -0.0721692287722941,
                -0.9973924014240395
            ]
        },
        {
            "radius": 0.001,
            "pos": [
                0.5966260940362305,
                0.5345286654454169
            ],
            "dir": [
                -0.08757559349685917,
                -0.9961578767563266
            ]
        },
        {
            "radius": 0.001,
            "pos": [
                0.5952961530633014,
                0.5206902774950811
            ],
            "dir": [
                -0.10397664022933174,
                -0.9945797395315371
            ]
        },
        {
            "radius": 0.001,
            "pos": [
                0.5937618562996132,
                0.507149874482665
            ],
            "dir": [
                -0.12144894979258729,
                -0.9925976791199331
            ]
        },
        {
            "radius": 0.001,
            "pos": [
                0.5920183187461836,
                0.4939172264061334
            ],
            "dir": [
                -0.14007473239318408,
                -0.9901409340821022
            ]
        },
        {
            "radius": 0.001,
            "pos": [
                0.5900606554040302,
                0.4810021032634507
            ],
            "dir": [
                -0.15994171073413516,
                -0.9871264605750564
            ]
        },
        {
            "radius": 0.001,
            "pos": [
                0.5878839812741705,
                0.4684142750525816
            ],
            "dir": [
                -0.18114274062241376,
                -0.9834568152795531
            ]
        },
        {
            "radius": 0.001,
            "pos": [
                0.5854834113576226,
                0.4561635117714906
            ],
            "dir": [
                -0.20377505836523663,
                -0.9790177350733972
            ]
        },
        {
            "radius": 0.001,
            "pos": [
                0.582854060655404,
                0.4442595834181423
            ],
            "dir": [
                -0.2279390092664517,
                -0.9736754120622686
            ]
        },
        {
            "radius": 0.001,
            "pos": [
                0.5799910441685325,
                0.4327122599905014
            ],
            "dir": [
                -0.25373606916756447,
                -0.9672734914197706
            ]
        },
        {
            "radius": 0.001,
            "pos": [
                0.5768894768980257,
                0.42153131148653233
            ],
            "dir": [
                -0.2812659221249258,
                -0.9596298666940369
            ]
        },
        {
            "radius": 0.001,
            "pos": [
                0.5735444738449014,
                0.41072650790419973
            ],
            "dir": [
                -0.31062230525533574,
                -0.9505334204949665
            ]
        },
        {
            "radius": 0.001,
            "pos": [
                0.569951150010177,
                0.4003076192414683
            ],
            "dir": [
                -0.34188728395117707,
                -0.9397409670076575
            ]
        },
        {
            "radius": 0.001,
            "pos": [
                0.5661046203948708,
                0.3902844154963024
            ],
            "dir": [
                -0.37512359117295113,
                -0.9269748062086199
            ]
        },
        {
            "radius": 0.001,
            "pos": [
                0.562,
                0.3806666666666667
            ],
            "dir": [
                -0.4107812272039315,
                -0.9117339433062871
            ]
        },
        {
            "radius": 0.001,
            "pos": [
                0.5553934152632378,
                0.3670872401759976
            ],
            "dir": [
                -0.46501642333960647,
                -0.885302053552594
            ]
        },
        {
            "radius": 0.001,
            "pos": [
                0.5481769079047185,
                0.3543744500075861
            ],
            "dir": [
                -0.5230277071550586,
                -0.8523156795155902
            ]
        },
        {
            "radius": 0.001,
            "pos": [
                0.5403322712790168,
                0.34256653011682603
            ],
            "dir": [
                -0.5842103458637603,
                -0.8116022867055919
            ]
        },
        {
            "radius": 0.001,
            "pos": [
                0.5318412987407071,
                0.3317017144591109
            ],
            "dir": [
                -0.6475106768016745,
                -0.7620563781163685
            ]
        },
        {
            "radius": 0.001,
            "pos": [
                0.5226857836443635,
                0.32181823698983464
            ],
            "dir": [
                -0.7113570247727117,
                -0.7028308354835575
            ]
        },
        {
            "radius": 0.001,
            "pos": [
                0.5128475193445607,
                0.31295433166439085
            ],
            "dir": [
                -0.7736737918330827,
                -0.6335841410820033
            ]
        },
        {
            "radius": 0.001,
            "pos": [
                0.5023082991958732,
                0.3051482324381733
            ],
            "dir": [
                -0.8320289043890203,
                -0.554732279808203
            ]
        },
        {
            "radius": 0.001,
            "pos": [
                0.49104991655287517,
                0.2984381732665756
            ],
            "dir": [
                -0.883932685014768,
                -0.46761416612692913
            ]
        },
        {
            "radius": 0.001,
            "pos": [
                0.4790541647701411,
                0.29286238810499166
            ],
            "dir": [
                -0.9272386477351048,
                -0.37447094699906214
            ]
        },
        {
            "radius": 0.001,
            "pos": [
                0.4663028372022455,
                0.2884591109088151
            ],
            "dir": [
                -0.9605254195311188,
                -0.2781922328796552
            ]
        },
        {
            "radius": 0.001,
            "pos": [
                0.45277772720376275,
                0.28526657563343955
            ],
            "dir": [
                -0.9833199417171703,
                -0.18188428250220148
            ]
        },
        {
            "radius": 0.001,
            "pos": [
                0.4384606281292672,
                0.2833230162342589
            ],
            "dir": [
                -0.9960848253955652,
                -0.08840260525960997
            ]
        },
        {
            "radius": 0.001,
            "pos": [
                0.42333333333333334,
                0.2826666666666667
            ],
            "dir": [
                -1.0,
                0.0
            ]
        },
        {
            "radius": 0.001,
            "pos": [
                0.40208164287503134,
                0.2835917856248435
            ],
            "dir": [
                -0.995743242508732,
                0.0921704670607476
            ]
        },
        {
            "radius": 0.001,
            "pos": [
                0.3836669171049336,
                0.28629902329075885
            ],
            "dir": [
                -0.9788489047534827,
                0.2045845098312857
            ]
        },
        {
            "radius": 0.001,
            "pos": [
                0.36791785624843476,
                0.2906862008514901
            ],
            "dir": [
                -0.9412456546454234,
                0.3377226933611486
            ]
        },
        {
            "radius": 0.001,
            "pos": [
                0.35466316053092917,
                0.2966511394941147
            ],
            "dir": [
                -0.8736281103135215,
                0.4865942096552583
            ]
        },
        {
            "radius": 0.001,
            "pos": [
                0.3437315301778112,
                0.30409166040571
            ],
            "dir": [
                -0.7699554546321942,
                0.6380976397716349
            ]
        },
        {
            "radius": 0.001,
            "pos": [
                0.33495166541447535,
                0.3129055847733534
            ],
            "dir": [
                -0.6340061875558923,
                0.7733279732046701
            ]
        },
        {
            "radius": 0.001,
            "pos": [
                0.32815226646631607,
                0.32299073378412224
            ],
            "dir": [
                -0.4811993850543158,
                0.8766111748223087
            ]
        },
        {
            "radius": 0.001,
            "pos": [
                0.3231620335587278,
                0.3342449286250939
            ],
            "dir": [
                -0.33114212221882194,
                0.9435808894273001
            ]
        },
        {
            "radius": 0.001,
            "pos": [
                0.31980966691710494,
                0.34656599048334585
            ],
            "dir": [
                -0.19805993968480223,
                0.9801899103194505
            ]
        },
        {
            "radius": 0.001,
            "pos": [
                0.31792386676684203,
                0.3598517405459554
            ],
            "dir": [
                -0.0877347719226557,
                0.9961438700286619
            ]
        },
        {
            "radius": 0.001,
            "pos": [
                0.31733333333333336,
                0.374
            ],
            "dir": [
                0.0,
                1.0
            ]
        },
        {
            "radius": 0.001,
            "pos": [
                0.3180638024691358,
                0.3874022716049383
            ],
            "dir": [
                0.10980371215682823,
                0.9939532910537499
            ]
        },
        {
            "radius": 0.001,
            "pos": [
                0.32019041975308643,
                0.4001692839506173
            ],
            "dir": [
                0.21862995335725957,
                0.9758078414805871
            ]
        },
        {
            "radius": 0.001,
            "pos": [
                0.323616,
                0.41234133333333334
            ],
            "dir": [
                0.3219560351446134,
                0.9467546204978144
            ]
        },
        {
            "radius": 0.001,
            "pos": [
                0.3282433580246914,
                0.42395871604938273
            ],
            "dir": [
                0.41613659115355156,
                0.9093021156376475
            ]
        },
        {
            "radius": 0.001,
            "pos": [
                0.33397530864197533,
                0.43506172839506174
            ],
            "dir": [
                0.4989375367350903,
                0.8666379488787231
            ]
        },
        {
            "radius": 0.001,
            "pos": [
                0.34071466666666667,
                0.4456906666666667
            ],
            "dir": [
                0.5695823396594976,
                0.821934278606272
            ]
        },
        {
            "radius": 0.001,
            "pos": [
                0.34836424691358026,
                0.45588582716049386
            ],
            "dir": [
                0.6284348215621605,
                0.7778622468330338
            ]
        },
        {
            "radius": 0.001,
            "pos": [
                0.35682686419753085,
                0.46568750617283955
            ],
            "dir": [
                0.6765521555273726,
                0.7363947181038617
            ]
        },
        {
            "radius": 0.001,
            "pos": [
                0.36600533333333335,
                0.475136
            ],
            "dir": [
                0.7152875174996546,
                0.6988302850543765
            ]
        },
        {
            "radius": 0.001,
            "pos": [
                0.3758024691358025,
                0.4842716049382716
            ],
            "dir": [
                0.7460155189588735,
                0.6659285588353472
            ]
        },
        {
            "radius": 0.001,
            "pos": [
                0.38612108641975307,
                0.49313461728395064
            ],
            "dir": [
                0.769977229099068,
                0.6380713648714549
            ]
        },
        {
            "radius": 0.001,
            "pos": [
                0.396864,
                0.5017653333333334
            ],
            "dir": [
                0.7882110536393614,
                0.6154050169772162
            ]
        },
        {
            "radius": 0.001,
            "pos": [
                0.40793402469135803,
                0.510204049382716
            ],
            "dir": [
                0.8015341232601279,
                0.59794903566242
            ]
        },
        {
            "radius": 0.001,
            "pos": [
                0.41923397530864204,
                0.5184910617283951
            ],
            "dir": [
                0.810547904913658,
                0.5856723434140285
            ]
        },
        {
            "radius": 0.001,
            "pos": [
                0.4306666666666667,
                0.5266666666666666
            ],
            "dir": [
                0.939793423488437,
                0.3417430630867044
            ]
        },
        {
            "radius": 0.001,
            "pos": [
                0.43800000000000006,
                0.5293333333333334
            ],
            "dir": [
                0.806766093746736,
                0.5908709418990179
            ]
        },
        {
            "radius": 0.001,
            "pos": [
                0.44968788580246916,
                0.538025462962963
            ],
            "dir": [
                0.7970793015528452,
                0.60387464513426
            ]
        },
        {
            "radius": 0.001,
            "pos": [
                0.46100308641975307,
                0.5468148148148149
            ],
            "dir": [
                0.7811869267472338,
                0.6242971932334886
            ]
        },
        {
            "radius": 0.001,
            "pos": [
                0.47182291666666665,
                0.5557708333333333
            ],
            "dir": [
                0.7579850121223424,
                0.6522719688886626
            ]
        },
        {
            "radius": 0.001,
            "pos": [
                0.4820246913580247,
                0.564962962962963
            ],
            "dir": [
                0.7259526839058267,
                0.6877446479107832
            ]
        },
        {
            "radius": 0.001,
            "pos": [
                0.491485725308642,
                0.5744606481481482
            ],
            "dir": [
                0.6831676502864251,
                0.7302615706732244
            ]
        },
        {
            "radius": 0.001,
            "pos": [
                0.5000833333333333,
                0.5843333333333334
            ],
            "dir": [
                0.6274379404948931,
                0.7786665723064827
            ]
        },
        {
            "radius": 0.001,
            "pos": [
                0.5076948302469136,
                0.594650462962963
            ],
            "dir": [
                0.5566523246026079,
                0.8307455624404579
            ]
        },
        {
            "radius": 0.001,
            "pos": [
                0.5141975308641975,
                0.6054814814814815
            ],
            "dir": [
                0.4694421250264311,
                0.8829632445638202
            ]
        },
        {
            "radius": 0.001,
            "pos": [
                0.51946875,
                0.6168958333333334
            ],
            "dir": [
                0.3661125767449808,
                0.9305705675278746
            ]
        },
        {
            "radius": 0.001,
            "pos": [
                0.5233858024691358,
                0.628962962962963
            ],
            "dir": [
                0.24949579922075812,
                0.968375880622393
            ]
        },
        {
            "radius": 0.001,
            "pos": [
                0.5258260030864198,
                0.6417523148148148
            ],
            "dir": [
                0.1250860448532537,
                0.9921458972262949
            ]
        }
    ]
}
